iotdeviceprovisioner/Bootstrap.py
iotdeviceprovisioner/__init__.py
iotdeviceprovisioner-1.0.dist-info/DESCRIPTION.rst
iotdeviceprovisioner-1.0.dist-info/METADATA
iotdeviceprovisioner-1.0.dist-info/RECORD
iotdeviceprovisioner-1.0.dist-info/WHEEL
iotdeviceprovisioner-1.0.dist-info/metadata.json
iotdeviceprovisioner-1.0.dist-info/top_level.txt
